LICENSE
MANIFEST.in
README.md
requirements.txt
setup.py
version.txt
colossalai_platform/__init__.py
colossalai_platform.egg-info/PKG-INFO
colossalai_platform.egg-info/SOURCES.txt
colossalai_platform.egg-info/dependency_links.txt
colossalai_platform.egg-info/entry_points.txt
colossalai_platform.egg-info/requires.txt
colossalai_platform.egg-info/top_level.txt
colossalai_platform/cli/__init__.py
colossalai_platform/cli/aliased_group.py
colossalai_platform/cli/cli.py
colossalai_platform/cli/commands/__init__.py
colossalai_platform/cli/commands/template.py
colossalai_platform/cli/commands/templates/DataSchema.json
colossalai_platform/cli/commands/templates/Dockerfile
colossalai_platform/cli/commands/templates/HyperParameters.json
colossalai_platform/cli/commands/templates/README.md
colossalai_platform/cli/commands/templates/patch.py
colossalai_platform/cli/commands/templates/requirements.txt
colossalai_platform/cli/commands/templates/train.py
colossalai_platform/cli/commands/templates/train.sh