Metadata-Version: 2.1
Name: colossalai-platform
Version: 0.0.1
Summary: ColossalAI Platform CLI for ease
Home-page: https://github.com/hpcaitech/ColossalAI-Platform-CLI
License: Apache Software License 2.0
Project-URL: Github, https://github.com/hpcaitech/ColossalAI-Platform-CLI
Classifier: Programming Language :: Python :: 3
Classifier: License :: OSI Approved :: Apache Software License
Classifier: Topic :: Software Development :: Build Tools
Classifier: Topic :: System :: Distributed Computing
Requires-Python: >=3.6
License-File: LICENSE
